h2o_audit_trail/__init__.py
h2o_audit_trail/_version.py
h2o_audit_trail/connection_config.py
h2o_audit_trail/exception.py
h2o_audit_trail/login.py
h2o_audit_trail/auth/__init__.py
h2o_audit_trail/auth/token_api_client.py
h2o_audit_trail/event/__init__.py
h2o_audit_trail/event/client.py
h2o_audit_trail/event/create.py
h2o_audit_trail/event/event.py
h2o_audit_trail/event/event_type.py
h2o_audit_trail/event/search.py
h2o_audit_trail/gen/__init__.py
h2o_audit_trail/gen/api_client.py
h2o_audit_trail/gen/configuration.py
h2o_audit_trail/gen/exceptions.py
h2o_audit_trail/gen/model_utils.py
h2o_audit_trail/gen/rest.py
h2o_audit_trail/gen/api/__init__.py
h2o_audit_trail/gen/api/event_service_api.py
h2o_audit_trail/gen/apis/__init__.py
h2o_audit_trail/gen/model/__init__.py
h2o_audit_trail/gen/model/audittrailv1_status.py
h2o_audit_trail/gen/model/googlerpc_status.py
h2o_audit_trail/gen/model/protobuf_any.py
h2o_audit_trail/gen/model/search_events_request_filter.py
h2o_audit_trail/gen/model/v1_batch_create_events_request.py
h2o_audit_trail/gen/model/v1_batch_create_events_response.py
h2o_audit_trail/gen/model/v1_create_event_request.py
h2o_audit_trail/gen/model/v1_create_event_response.py
h2o_audit_trail/gen/model/v1_event.py
h2o_audit_trail/gen/model/v1_event_type.py
h2o_audit_trail/gen/model/v1_search_events_request.py
h2o_audit_trail/gen/model/v1_search_events_response.py
h2o_audit_trail/gen/models/__init__.py
h2o_audit_trail/model/__init__.py
h2o_audit_trail/model/rpc_status.py
h2o_audit_trail/model/status.py
h2o_audit_trail-1.4.0.dist-info/METADATA
h2o_audit_trail-1.4.0.dist-info/WHEEL
h2o_audit_trail-1.4.0.dist-info/RECORD
