Metadata-Version: 2.4
Name: h2o-audit-trail
Version: 1.4.0
Summary: Python client for H2O Audit Trail
Project-URL: Documentation, https://docs.h2o.ai/audit-trail/py/initialization
Author-email: "H2O.ai" <support@h2o.ai>
Requires-Python: >=3.8
Requires-Dist: h2o-authn>=1.0.0
Requires-Dist: h2o-cloud-discovery>=2.1.0
Requires-Dist: python-dateutil>=2.8.2
Requires-Dist: requests>=2.32.4
